hera_mc/__init__.py
hera_mc/autocorrelations.py
hera_mc/branch_scheme.py
hera_mc/cm_active.py
hera_mc/cm_dossier.py
hera_mc/cm_gen_sqlite.py
hera_mc/cm_handling.py
hera_mc/cm_hookup.py
hera_mc/cm_partconnect.py
hera_mc/cm_redis_corr.py
hera_mc/cm_revisions.py
hera_mc/cm_sysdef.py
hera_mc/cm_sysutils.py
hera_mc/cm_table_info.py
hera_mc/cm_transfer.py
hera_mc/cm_utils.py
hera_mc/correlator.py
hera_mc/daemon_status.py
hera_mc/db_check.py
hera_mc/geo_handling.py
hera_mc/geo_location.py
hera_mc/geo_sysdef.py
hera_mc/librarian.py
hera_mc/mc.py
hera_mc/mc_session.py
hera_mc/node.py
hera_mc/observations.py
hera_mc/qm.py
hera_mc/rtp.py
hera_mc/server_status.py
hera_mc/subsystem_error.py
hera_mc/utils.py
hera_mc/watch_dog.py
hera_mc/weather.py
hera_mc/data/.DS_Store
hera_mc/data/HERA_350.txt
hera_mc/data/__init__.py
hera_mc/data/nodes.txt
hera_mc/data/sysdef.json
hera_mc/data/__pycache__/__init__.cpython-36.pyc
hera_mc/data/__pycache__/__init__.cpython-37.pyc
hera_mc/data/__pycache__/__init__.cpython-38.pyc
hera_mc/data/__pycache__/__init__.cpython-39.pyc
hera_mc/data/test_data/corr_config_example.yaml
hera_mc/data/test_data/dump.rdb
hera_mc/data/test_data/example_firstcal_metrics.hdf5
hera_mc/data/test_data/hera_feng_config_example.yaml
hera_mc/data/test_data/initialization_data_apriori_antenna.csv
hera_mc/data/test_data/initialization_data_connections.csv
hera_mc/data/test_data/initialization_data_geo_location.csv
hera_mc/data/test_data/initialization_data_part_info.csv
hera_mc/data/test_data/initialization_data_part_rosetta.csv
hera_mc/data/test_data/initialization_data_parts.csv
hera_mc/data/test_data/initialization_data_station_type.csv
hera_mc/data/test_data/inserts.sql
hera_mc/data/test_data/schema.sql
hera_mc/tests/__init__.py
hera_mc/tests/conftest.py
hera_mc/tests/test_autocorrelations.py
hera_mc/tests/test_cm_transfer.py
hera_mc/tests/test_cm_utils.py
hera_mc/tests/test_connections.py
hera_mc/tests/test_correlator.py
hera_mc/tests/test_daemon_status.py
hera_mc-2.0.1.dist-info/LICENSE
hera_mc-2.0.1.dist-info/METADATA
hera_mc-2.0.1.dist-info/WHEEL
hera_mc-2.0.1.dist-info/top_level.txt
hera_mc-2.0.1.dist-info/RECORD
