Metadata-Version: 2.1
Name: hera-mc
Version: 2.0.1
Summary: hera_mc: HERA monitor and control
Home-page: https://github.com/HERA-Team/hera_mc
Author: HERA Team
Author-email: hera-sw@lists.berkeley.edu
License: BSD
Platform: UNKNOWN
Classifier: Development Status :: 4 - Beta
Classifier: Environment :: Console
Classifier: Intended Audience :: Science/Research
Classifier: License :: OSI Approved :: MIT License
Classifier: Operating System :: OS Independent
Classifier: Programming Language :: Python
Classifier: Programming Language :: Python :: 3.7
Classifier: Programming Language :: Python :: 3.8
Classifier: Programming Language :: Python :: 3.9
Classifier: Programming Language :: Python :: 3.10
Classifier: Topic :: Scientific/Engineering
License-File: LICENSE
Requires-Dist: alembic
Requires-Dist: astropy
Requires-Dist: cartopy
Requires-Dist: numpy
Requires-Dist: psycopg2
Requires-Dist: pyuvdata
Requires-Dist: pyyaml
Requires-Dist: redis
Requires-Dist: setuptools-scm
Requires-Dist: sqlalchemy
Provides-Extra: all
Requires-Dist: h5py ; extra == 'all'
Requires-Dist: pandas ; extra == 'all'
Requires-Dist: psutil ; extra == 'all'
Requires-Dist: python-dateutil ; extra == 'all'
Requires-Dist: tabulate ; extra == 'all'
Requires-Dist: tornado ; extra == 'all'
Provides-Extra: dev
Requires-Dist: h5py ; extra == 'dev'
Requires-Dist: pandas ; extra == 'dev'
Requires-Dist: psutil ; extra == 'dev'
Requires-Dist: python-dateutil ; extra == 'dev'
Requires-Dist: tabulate ; extra == 'dev'
Requires-Dist: tornado ; extra == 'dev'
Requires-Dist: pytest ; extra == 'dev'
Requires-Dist: pre-commit ; extra == 'dev'
Provides-Extra: sqlite
Requires-Dist: tabulate ; extra == 'sqlite'
